{
  "applications": [
    {
      "id": "b2c_iot",
      "name": "B2C IoT",
      "categoryId": "core",
      "description": "Re-contextualized impactful protocol",
      "investment_24m": "667",
      "hostedtype": "OnPremise",
      "licensing_cost": "141",
      "status_color": "#FF0000",
      "type": "InHouseDev",
      "support_cost": "203",
      "deployment_date": "9/11/16",
      "end_of_maintenance": "14/7/17",
      "department": "Product Management",
      "status": "Decomissioned",
      "end_of_life": "11/12/18",
      "months_to_renew_support": "22",
      "sme_email": "Ferdinand.MacKettrick@memento.net.au",
      "investment_number": "323",
      "integrations": [
        {
          "id": "int-185",
          "name": "INT-185",
          "categoryId": "0b92058e-25af-4e83-ad26-fe6e6f607f17",
          "description": "Proin interdum mauris non ligula pellentesque ultrices. Phasellus id sapien in sapien iaculis congue. Vivamus metus arcu, adipiscing molestie, hendrerit at, vulputate vitae, nisl.",
          "sourceApplicationId": "b2c_iot",
          "targetApplicationId": "tiger_web",
          "logical_server": "BATCH",
          "status_color": "#00FF00",
          "pattern": "Aggregator",
          "golive_date": "3/9/14",
          "sme_name": "Andie MacVanamy",
          "datacentre": "Dandenong",
          "department": "App Control",
          "status": "Active",
          "sme_email": "amacvanamy5@memento.net.au",
          "complexity": "High",
          "last_deployment_date": "29/6/15"
        }
      ]
    }
  ]
}